get_rectangle_infos/LICENSE
get_rectangle_infos/README.MD
get_rectangle_infos/__init__.py
get_rectangle_infos/requirements.txt
get_rectangle_infos/thirdparty.json
get_rectangle_infos-0.10.dist-info/LICENSE.rst
get_rectangle_infos-0.10.dist-info/METADATA
get_rectangle_infos-0.10.dist-info/WHEEL
get_rectangle_infos-0.10.dist-info/top_level.txt
get_rectangle_infos-0.10.dist-info/RECORD
